uiautomator/__init__.py
uiautomator/libs/app-uiautomator-androidx.apk
uiautomator/libs/app-uiautomator-test-androidx.apk
uiautomator/libs/app-uiautomator-test.apk
uiautomator/libs/app-uiautomator.apk
uiautomator/libs/bundle.jar
uiautomator/libs/uiautomator-stub.jar
uiautomator-1.0.1.dist-info/LICENSE
uiautomator-1.0.1.dist-info/METADATA
uiautomator-1.0.1.dist-info/NOTICE
uiautomator-1.0.1.dist-info/WHEEL
uiautomator-1.0.1.dist-info/top_level.txt
uiautomator-1.0.1.dist-info/RECORD
